pycovid19/__init__.py
pycovid19/covid19.py
pycovid19/jupyter_logo.png
pycovid19/masked_agent.png
pycovid19-0.1.4.dist-info/METADATA
pycovid19-0.1.4.dist-info/WHEEL
pycovid19-0.1.4.dist-info/top_level.txt
pycovid19-0.1.4.dist-info/RECORD
