Metadata-Version: 2.1
Name: pycovid19
Version: 0.1.4
Summary: Protect you jupyter notebook from COVID19
Home-page: https://github.com/sobir-git/covid19
Author: Sobir Bobiev
Author-email: sobir.bobiev@gmail.com
License: MIT
Download-URL: https://pypi.org/project/pycovid19/
Keywords: Jupyter Notebook,COVID19,Protective Masks
Platform: UNKNOWN
Requires-Dist: ipython (>=5.0.0)
